nhl/__init__.py
nhl/sdk.py
nhl/hooks/__init__.py
nhl/hooks/hook.py
nhl/models/__init__.py
nhl/models/base.py
nhl/models/conference.py
nhl/models/conferences.py
nhl/models/division.py
nhl/models/divisions.py
nhl/models/draft.py
nhl/models/draft_prospect.py
nhl/models/draft_prospects.py
nhl/models/franchise.py
nhl/models/game.py
nhl/models/game_boxscore.py
nhl/models/game_boxscore_team.py
nhl/models/game_boxscores.py
nhl/models/game_content.py
nhl/models/game_decision_player.py
nhl/models/game_editorial.py
nhl/models/game_editorial_keyword.py
nhl/models/game_editorials.py
nhl/models/game_highlight.py
nhl/models/game_highlights.py
nhl/models/game_highlights_game_center_2.py
nhl/models/game_linescore.py
nhl/models/game_linescore_team.py
nhl/models/game_official.py
nhl/models/game_period.py
nhl/models/game_play.py
nhl/models/get_player_stats_stats.py
nhl/models/get_schedule_expand.py
nhl/models/get_standings_by_type_type.py
nhl/models/get_teams_expand.py
nhl/models/photo.py
nhl/models/player.py
nhl/models/player_stats.py
nhl/models/players.py
nhl/models/roster.py
nhl/models/rosters.py
nhl/models/schedule.py
nhl/models/schedule_day.py
nhl/models/schedule_game.py
nhl/models/standing_types.py
nhl/models/standings.py
nhl/models/stat_types.py
nhl/models/team.py
nhl/models/team_stats.py
nhl/models/teams.py
nhl/models/venue.py
nhl/models/utils/cast_models.py
nhl/models/utils/json_map.py
nhl/net/__init__.py
nhl/net/environment/__init__.py
nhl/net/environment/environment.py
nhl/net/headers/__init__.py
nhl/net/headers/base_header.py
nhl/net/request_chain/__init__.py
nhl/net/request_chain/request_chain.py
nhl/net/request_chain/handlers/__init__.py
nhl/net/request_chain/handlers/base_handler.py
nhl/net/request_chain/handlers/hook_handler.py
nhl/net/request_chain/handlers/http_handler.py
nhl/net/request_chain/handlers/retry_handler.py
nhl/net/transport/__init__.py
nhl/net/transport/request.py
nhl/net/transport/request_error.py
nhl/net/transport/response.py
nhl_client-1.0.0.dist-info/LICENSE
nhl_client-1.0.0.dist-info/METADATA
nhl_client-1.0.0.dist-info/WHEEL
nhl_client-1.0.0.dist-info/top_level.txt
nhl_client-1.0.0.dist-info/RECORD
