Metadata-Version: 2.1
Name: nhl-client
Version: 1.0.0
Summary: Documenting the publicly accessible portions of the NHL API.
License: MIT
Requires-Python: >=3.7
License-File: LICENSE
Requires-Dist: requests >=2.31.0
